fs_rclone/__init__.py
fs_rclone-0.1.2.dist-info/METADATA
fs_rclone-0.1.2.dist-info/WHEEL
fs_rclone-0.1.2.dist-info/licenses/LICENSE
fs_rclone-0.1.2.dist-info/RECORD
