Metadata-Version: 2.3
Name: fs-rclone
Version: 0.1.2
Summary: Access rclone from a pyfilesystem interface.
Project-URL: Homepage, https://github.com/element0/fs_rclone
Project-URL: Issues, https://github.com/element0/fs_rclone/issues
Author-email: Raygan Henley <raygan@raygan.com>
License-File: LICENSE
Classifier: License :: OSI Approved :: MIT License
Classifier: Operating System :: OS Independent
Classifier: Programming Language :: Python :: 3
Requires-Python: >=3.10
Requires-Dist: fs==2.4.12
Requires-Dist: rclone-python==0.1.12
